word_document_content_adder/__init__.py
word_document_content_adder/main.py
word_document_content_adder/tools.py
word_document_content_adder/utils.py
word_document_content_adder_mcp-1.1.0.dist-info/METADATA
word_document_content_adder_mcp-1.1.0.dist-info/WHEEL
word_document_content_adder_mcp-1.1.0.dist-info/entry_points.txt
word_document_content_adder_mcp-1.1.0.dist-info/top_level.txt
word_document_content_adder_mcp-1.1.0.dist-info/RECORD
