Metadata-Version: 2.4
Name: word-document-content-adder-mcp
Version: 1.1.0
Summary: Word文档内容添加MCP服务 - 提供文档内容添加相关功能
Author-email: Word MCP Services <support@example.com>
License: MIT
Requires-Python: >=3.10
Requires-Dist: python-docx>=1.1.0
Requires-Dist: fastmcp>=2.8.1
Requires-Dist: Pillow>=10.0.0
